{
  "alpinevpn": {
    "commit_message": "Make iface prefixes configurable with VPN_INTERFACE_PREFIXES, thx to salty from Saltbox",
    "commit_sha": "3043df98fff03732b776a914d55026e4ca0a4b6d",
    "description": "Alpine 3.22",
    "hide": false,
    "last_updated": "2026-01-16T11:46:45.000Z",
    "last_updated_url": "https://github.com/hotio/base/actions/runs/21065591731",
    "tags": [
      "",
      "alpinevpn",
      "alpinevpn-3043df9",
      "",
      "",
      "",
      ""
    ]
  },
  "noblevpn": {
    "commit_message": "this is silly",
    "commit_sha": "b3fe62506ef35252ce1d872d1026842715b2fb58",
    "description": "Ubuntu 24.04",
    "hide": false,
    "last_updated": "2026-01-16T11:12:56.000Z",
    "last_updated_url": "https://github.com/hotio/base/actions/runs/21064755730",
    "tags": [
      "",
      "noblevpn",
      "noblevpn-b3fe625",
      "",
      "",
      "",
      ""
    ]
  }
}
