{
  "alpinevpn": {
    "commit_message": "tweak proton port forwarding loops",
    "commit_sha": "1d9f62fc6e9625673d758ca162cb29b353311b2d",
    "description": "Alpine 3.22",
    "hide": false,
    "last_updated": "2026-01-21T05:01:42.000Z",
    "last_updated_url": "https://github.com/hotio/base/actions/runs/21197880977",
    "tags": [
      "",
      "alpinevpn",
      "alpinevpn-1d9f62f",
      "",
      "",
      "",
      ""
    ]
  },
  "noblevpn": {
    "commit_message": "tweak proton port forwarding loops",
    "commit_sha": "6eb95033b279aa2c0c8b252d4462178c58d3f5e3",
    "description": "Ubuntu 24.04",
    "hide": false,
    "last_updated": "2026-01-21T05:02:01.000Z",
    "last_updated_url": "https://github.com/hotio/base/actions/runs/21197888274",
    "tags": [
      "",
      "noblevpn",
      "noblevpn-6eb9503",
      "",
      "",
      "",
      ""
    ]
  }
}
