{
  "release": {
    "commit_message": "Version update: 0.24.739 => 0.24.752",
    "commit_sha": "19aa645cbf05e2e0260768c9361ef12a2af97ccd",
    "description": "Releases",
    "hide": false,
    "last_updated": "2026-01-07T05:56:33.000Z",
    "last_updated_url": "https://github.com/hotio/jackett/actions/runs/20772143221",
    "latest": true,
    "tags": [
      "release",
      "release-0.24.752",
      "release-19aa645",
      "release-v0",
      "release-v0.24",
      "release-v0.24.752"
    ]
  },
  "testing": {
    "commit_message": "Version update: 0.24.739 => 0.24.752",
    "commit_sha": "8d5f7c021682a72060d264840f3036edf993b58c",
    "description": "Pre-releases",
    "hide": false,
    "last_updated": "2026-01-07T05:56:35.000Z",
    "last_updated_url": "https://github.com/hotio/jackett/actions/runs/20772143804",
    "latest": false,
    "tags": [
      "testing",
      "testing-0.24.752",
      "testing-8d5f7c0",
      "testing-v0",
      "testing-v0.24",
      "testing-v0.24.752"
    ]
  }
}
