{
  "release": {
    "commit_message": "Modified: meta.json",
    "commit_sha": "f1326d02d5fa3c933caacb185b1ec19671d71df1",
    "description": "Releases",
    "hide": false,
    "last_updated": "2026-07-12T08:02:43.000Z",
    "last_updated_url": "https://github.com/hotio/jackett/actions/runs/29185203955",
    "tags": [
      "latest",
      "release",
      "release-f1326d0",
      "release-0.24.2206",
      "release-v0",
      "release-v0.24",
      "release-v0.24.2206"
    ]
  },
  "testing": {
    "commit_message": "Modified: meta.json",
    "commit_sha": "9c231086bc194a0427c5cabbf5d3010350ca3f83",
    "description": "Pre-releases",
    "hide": false,
    "last_updated": "2026-07-12T08:02:45.000Z",
    "last_updated_url": "https://github.com/hotio/jackett/actions/runs/29185204797",
    "tags": [
      "",
      "testing",
      "testing-9c23108",
      "testing-0.24.2206",
      "testing-v0",
      "testing-v0.24",
      "testing-v0.24.2206"
    ]
  }
}
