{
  "release": {
    "commit_message": "Modified: meta.json",
    "commit_sha": "07d37c7f959a977a225a6cf57fd5675468730ee7",
    "description": "Releases",
    "hide": false,
    "last_updated": "2026-06-22T21:28:52.000Z",
    "last_updated_url": "https://github.com/hotio/jackett/actions/runs/27985274938",
    "tags": [
      "latest",
      "release",
      "release-07d37c7",
      "release-0.24.2108",
      "release-v0",
      "release-v0.24",
      "release-v0.24.2108"
    ]
  },
  "testing": {
    "commit_message": "Modified: meta.json",
    "commit_sha": "754053ea1d40f6ecf006ba97abb4db4d36bac8d0",
    "description": "Pre-releases",
    "hide": false,
    "last_updated": "2026-06-23T06:41:38.000Z",
    "last_updated_url": "https://github.com/hotio/jackett/actions/runs/28007499242",
    "tags": [
      "",
      "testing",
      "testing-754053e",
      "testing-0.24.2110",
      "testing-v0",
      "testing-v0.24",
      "testing-v0.24.2110"
    ]
  }
}
