{
  "release": {
    "commit_message": "Version update: 0.24.1465 => 0.24.1470",
    "commit_sha": "a938454d8d9e9e946d75f4d1d0720c3113959fcc",
    "description": "Releases",
    "hide": false,
    "last_updated": "2026-03-27T06:39:47.000Z",
    "last_updated_url": "https://github.com/hotio/jackett/actions/runs/23634556553",
    "tags": [
      "latest",
      "release",
      "release-a938454",
      "release-0.24.1470",
      "release-v0",
      "release-v0.24",
      "release-v0.24.1470"
    ]
  },
  "testing": {
    "commit_message": "Version update: 0.24.1465 => 0.24.1470",
    "commit_sha": "3b8a26fa1300fa7431d2e6d7f02b6fab51a1ea2b",
    "description": "Pre-releases",
    "hide": false,
    "last_updated": "2026-03-27T06:39:49.000Z",
    "last_updated_url": "https://github.com/hotio/jackett/actions/runs/23634557023",
    "tags": [
      "",
      "testing",
      "testing-3b8a26f",
      "testing-0.24.1470",
      "testing-v0",
      "testing-v0.24",
      "testing-v0.24.1470"
    ]
  }
}
