{
  "release": {
    "commit_message": "Version update: 8.5.1 => 8.5.2",
    "commit_sha": "1ab93963dfaaa763152e4afe36624a98873bb63d",
    "description": "Releases",
    "hide": false,
    "last_updated": "2026-03-12T20:03:42.000Z",
    "last_updated_url": "https://github.com/hotio/nzbhydra2/actions/runs/23021396384",
    "tags": [
      "latest",
      "release",
      "release-1ab9396",
      "release-8.5.2",
      "release-v8",
      "release-v8.5",
      "release-v8.5.2"
    ]
  },
  "testing": {
    "commit_message": "Version update: 8.5.1 => 8.5.2",
    "commit_sha": "082de55489748109d57e9990a211cd4efd744b23",
    "description": "Pre-releases",
    "hide": false,
    "last_updated": "2026-03-12T20:03:43.000Z",
    "last_updated_url": "https://github.com/hotio/nzbhydra2/actions/runs/23021397104",
    "tags": [
      "",
      "testing",
      "testing-082de55",
      "testing-8.5.2",
      "testing-v8",
      "testing-v8.5",
      "testing-v8.5.2"
    ]
  }
}
