{
  "nightly": {
    "commit_message": "Upstream update: alpinevpn-489d5d6 => alpinevpn-5648cae",
    "commit_sha": "80898bbbe594b85d82dd5c160706c2539b2fd508",
    "description": "Every commit to develop",
    "hide": false,
    "last_updated": "2026-01-22T10:19:18.000Z",
    "last_updated_url": "https://github.com/hotio/overseerr/actions/runs/21244703912",
    "tags": [
      "",
      "nightly",
      "nightly-80898bb",
      "nightly-5ef098f6d844dde6d5d9076c8814e9a34bd73451",
      "",
      "",
      ""
    ]
  },
  "release": {
    "commit_message": "Upstream update: alpinevpn-489d5d6 => alpinevpn-5648cae",
    "commit_sha": "f55532e315d15cbd62e039887c6cabadc42d03fb",
    "description": "Releases",
    "hide": false,
    "last_updated": "2026-01-22T10:19:20.000Z",
    "last_updated_url": "https://github.com/hotio/overseerr/actions/runs/21244704891",
    "tags": [
      "latest",
      "release",
      "release-f55532e",
      "release-1.34.0",
      "release-v1",
      "release-v1.34",
      "release-v1.34.0"
    ]
  }
}
