{
  "nightly": {
    "commit_message": "Upstream update: alpinevpn-c2217dd => alpinevpn-6480c7b",
    "commit_sha": "65b6024e4acb7e28e99c1a9892f4705e63268e2a",
    "description": "nightly",
    "hide": false,
    "last_updated": "2026-01-18T14:57:07.000Z",
    "last_updated_url": "https://github.com/hotio/prowlarr/actions/runs/21113697247",
    "tags": [
      "",
      "nightly",
      "nightly-65b6024",
      "nightly-2.3.2.5251",
      "",
      "",
      ""
    ]
  },
  "release": {
    "commit_message": "Upstream update: alpinevpn-c2217dd => alpinevpn-6480c7b",
    "commit_sha": "07deb0207c4349a7f16d78ce4ef76d320bc307b7",
    "description": "master",
    "hide": false,
    "last_updated": "2026-01-18T14:57:09.000Z",
    "last_updated_url": "https://github.com/hotio/prowlarr/actions/runs/21113697666",
    "tags": [
      "latest",
      "release",
      "release-07deb02",
      "release-2.3.0.5236",
      "",
      "",
      ""
    ]
  },
  "testing": {
    "commit_message": "Upstream update: alpinevpn-c2217dd => alpinevpn-6480c7b",
    "commit_sha": "815ec9bd5ecbb66d67ec38534d1020b371728100",
    "description": "develop",
    "hide": false,
    "last_updated": "2026-01-18T14:57:10.000Z",
    "last_updated_url": "https://github.com/hotio/prowlarr/actions/runs/21113697738",
    "tags": [
      "",
      "testing",
      "testing-815ec9b",
      "testing-2.3.2.5245",
      "",
      "",
      ""
    ]
  }
}
