{
  "nightly": {
    "commit_message": "Modified: meta.json",
    "commit_sha": "39f24b2311f1ebf7bdc279aa47c2a272d2c2fd7d",
    "description": "nightly",
    "hide": false,
    "last_updated": "2026-05-30T23:52:35.000Z",
    "last_updated_url": "https://github.com/hotio/prowlarr/actions/runs/26698243693",
    "tags": [
      "",
      "nightly",
      "nightly-39f24b2",
      "nightly-2.4.0.5391",
      "",
      "",
      ""
    ]
  },
  "release": {
    "commit_message": "Version, Upstream or Packages update",
    "commit_sha": "fb533f116ce8fbef988623a61757c3f362b232af",
    "description": "master",
    "hide": false,
    "last_updated": "2026-05-17T08:57:40.000Z",
    "last_updated_url": "https://github.com/hotio/prowlarr/actions/runs/25986472604",
    "tags": [
      "latest",
      "release",
      "release-fb533f1",
      "release-2.3.5.5327",
      "",
      "",
      ""
    ]
  },
  "testing": {
    "commit_message": "Modified: meta.json",
    "commit_sha": "ebdb2c23d442dcd435dbb15bdd6b62dea94c55d5",
    "description": "develop",
    "hide": false,
    "last_updated": "2026-05-31T19:03:03.000Z",
    "last_updated_url": "https://github.com/hotio/prowlarr/actions/runs/26721666675",
    "tags": [
      "",
      "testing",
      "testing-ebdb2c2",
      "testing-2.4.0.5391",
      "",
      "",
      ""
    ]
  }
}
