{
  "nightly": {
    "commit_message": "Version update: 90798e5e4dcbd2e45bc0aa36f95de482e08b8cea => b942e06297ab039a6ff848d5e479ec374ab907f2",
    "commit_sha": "3e1a5a52e7888aad33cc5661b997fcc9e7e30314",
    "description": "Every commit to develop",
    "hide": false,
    "last_updated": "2026-05-13T13:30:28.000Z",
    "last_updated_url": "https://github.com/hotio/sabnzbd/actions/runs/25802298354",
    "tags": [
      "",
      "nightly",
      "nightly-3e1a5a5",
      "nightly-b942e06297ab039a6ff848d5e479ec374ab907f2",
      "",
      "",
      ""
    ]
  },
  "release": {
    "commit_message": "Upstream or Packages File update",
    "commit_sha": "9c7f3d85b39622d4ef56cdff3a48d7e455fd3415",
    "description": "Releases",
    "hide": false,
    "last_updated": "2026-05-12T05:17:26.000Z",
    "last_updated_url": "https://github.com/hotio/sabnzbd/actions/runs/25714979976",
    "tags": [
      "latest",
      "release",
      "release-9c7f3d8",
      "release-5.0.1",
      "release-v5",
      "release-v5.0",
      "release-v5.0.1"
    ]
  },
  "testing": {
    "commit_message": "Upstream or Packages File update",
    "commit_sha": "da1fb62b1ef083c7ce799c6e06bedb48940c678e",
    "description": "Pre-releases",
    "hide": false,
    "last_updated": "2026-05-12T05:17:31.000Z",
    "last_updated_url": "https://github.com/hotio/sabnzbd/actions/runs/25714982563",
    "tags": [
      "",
      "testing",
      "testing-da1fb62",
      "testing-5.0.2RC1",
      "",
      "",
      ""
    ]
  }
}
