{
  "nightly": {
    "commit_message": "Version update: bf412371358ed3773c5f0fff65400c9d1547bdc9 => 27d222943c6988b34f047ac14acc5cdb3efedc5a",
    "commit_sha": "956fa369c94552bf31d94bf36140be8213b6ff75",
    "description": "Every commit to develop",
    "hide": false,
    "last_updated": "2026-01-19T11:45:50.000Z",
    "last_updated_url": "https://github.com/hotio/sabnzbd/actions/runs/21136260370",
    "tags": [
      "",
      "nightly",
      "nightly-956fa36",
      "nightly-27d222943c6988b34f047ac14acc5cdb3efedc5a",
      "",
      "",
      ""
    ]
  },
  "release": {
    "commit_message": "Upstream update: alpinevpn-5063227 => alpinevpn-7a36f80",
    "commit_sha": "9f4e3ab9e755a9785ff1a9cd300f5cbe3792ae44",
    "description": "Releases",
    "hide": false,
    "last_updated": "2026-01-19T09:31:04.000Z",
    "last_updated_url": "https://github.com/hotio/sabnzbd/actions/runs/21132234643",
    "tags": [
      "latest",
      "release",
      "release-9f4e3ab",
      "release-4.5.5",
      "release-v4",
      "release-v4.5",
      "release-v4.5.5"
    ]
  },
  "testing": {
    "commit_message": "Upstream update: alpinevpn-5063227 => alpinevpn-7a36f80",
    "commit_sha": "14db359f866b40f2db27f929eb06666932acda65",
    "description": "Pre-releases",
    "hide": false,
    "last_updated": "2026-01-19T09:31:05.000Z",
    "last_updated_url": "https://github.com/hotio/sabnzbd/actions/runs/21132235236",
    "tags": [
      "",
      "testing",
      "testing-14db359",
      "testing-4.6.0Beta2",
      "",
      "",
      ""
    ]
  }
}
