{
  "nightly": {
    "commit_message": "Modified: meta.json",
    "commit_sha": "090a597cc25be14772085da659b05760b86b8c53",
    "description": "Every commit to develop",
    "hide": false,
    "last_updated": "2026-06-26T17:46:38.000Z",
    "last_updated_url": "https://github.com/hotio/sabnzbd/actions/runs/28255360519",
    "tags": [
      "",
      "nightly",
      "nightly-090a597",
      "nightly-1b368a4278cca72bc78beb0a2407234cfd8e28aa",
      "",
      "",
      ""
    ]
  },
  "release": {
    "commit_message": "Modified: meta.json",
    "commit_sha": "f242b9fd1f72aaa4fa3dabd9a872d8497eab7f11",
    "description": "Releases",
    "hide": false,
    "last_updated": "2026-06-22T22:01:06.000Z",
    "last_updated_url": "https://github.com/hotio/sabnzbd/actions/runs/27986957234",
    "tags": [
      "latest",
      "release",
      "release-f242b9f",
      "release-5.0.4",
      "release-v5",
      "release-v5.0",
      "release-v5.0.4"
    ]
  },
  "testing": {
    "commit_message": "Modified: meta.json",
    "commit_sha": "f996a499b02aef97f934b3b2269cc1d639a2f1b9",
    "description": "Pre-releases",
    "hide": false,
    "last_updated": "2026-06-26T15:22:49.000Z",
    "last_updated_url": "https://github.com/hotio/sabnzbd/actions/runs/28247600377",
    "tags": [
      "",
      "testing",
      "testing-f996a49",
      "testing-5.1.0Beta2",
      "",
      "",
      ""
    ]
  }
}
