{
  "nightly": {
    "commit_message": "Upstream update: alpinevpn-0fe4477 => alpinevpn-4ed63ea",
    "commit_sha": "b090d9ac9fc5f9e178c7509424e599f54d1e383c",
    "description": "Every commit to develop",
    "hide": false,
    "last_updated": "2026-05-11T10:24:39.000Z",
    "last_updated_url": "https://github.com/hotio/sabnzbd/actions/runs/25664511373",
    "tags": [
      "",
      "nightly",
      "nightly-b090d9a",
      "nightly-7abb39d02d7833cc929e1379b0be6e9bfe7d5bd7",
      "",
      "",
      ""
    ]
  },
  "release": {
    "commit_message": "Upstream update: alpinevpn-b1ea9d4 => alpinevpn-0fe4477",
    "commit_sha": "70618c1d37e8e032d3c5248918168c80911efd96",
    "description": "Releases",
    "hide": false,
    "last_updated": "2026-05-09T15:44:05.000Z",
    "last_updated_url": "https://github.com/hotio/sabnzbd/actions/runs/25605060339",
    "tags": [
      "latest",
      "release",
      "release-70618c1",
      "release-5.0.1",
      "release-v5",
      "release-v5.0",
      "release-v5.0.1"
    ]
  },
  "testing": {
    "commit_message": "Upstream update: alpinevpn-b1ea9d4 => alpinevpn-0fe4477",
    "commit_sha": "9b582f1b2e0a2a2b8850acc7f644cfc2e5e7f5a2",
    "description": "Pre-releases",
    "hide": false,
    "last_updated": "2026-05-09T15:44:06.000Z",
    "last_updated_url": "https://github.com/hotio/sabnzbd/actions/runs/25605060804",
    "tags": [
      "",
      "testing",
      "testing-9b582f1",
      "testing-5.0.2RC1",
      "",
      "",
      ""
    ]
  }
}
