{
  "nightly": {
    "commit_message": "Version update: cd5acde5d2df26b54ff0c904a3a03ea4a96ab781 => f2d4347e1b0afbc0ce053b4d6d3dc9b92f14a966",
    "commit_sha": "5071b473443ea427e242e6b9519b5c66b84c77bf",
    "description": "Every commit to develop",
    "hide": false,
    "last_updated": "2026-03-25T07:09:48.000Z",
    "last_updated_url": "https://github.com/hotio/sabnzbd/actions/runs/23529266413",
    "tags": [
      "",
      "nightly",
      "nightly-5071b47",
      "nightly-f2d4347e1b0afbc0ce053b4d6d3dc9b92f14a966",
      "",
      "",
      ""
    ]
  },
  "release": {
    "commit_message": "Upstream update: alpinevpn-e5bbee4 => alpinevpn-9abb66b",
    "commit_sha": "48d37cb3372619463a25e66c0e4e9e4195bca12c",
    "description": "Releases",
    "hide": false,
    "last_updated": "2026-02-23T03:44:18.000Z",
    "last_updated_url": "https://github.com/hotio/sabnzbd/actions/runs/22292136862",
    "tags": [
      "latest",
      "release",
      "release-48d37cb",
      "release-4.5.5",
      "release-v4",
      "release-v4.5",
      "release-v4.5.5"
    ]
  },
  "testing": {
    "commit_message": "Version update: 5.0.0Beta3 => 5.0.0Beta4",
    "commit_sha": "c51e2bdc07b3554e9cb138a1c1dd4a6e02d64a03",
    "description": "Pre-releases",
    "hide": false,
    "last_updated": "2026-03-20T23:03:47.000Z",
    "last_updated_url": "https://github.com/hotio/sabnzbd/actions/runs/23366053820",
    "tags": [
      "",
      "testing",
      "testing-c51e2bd",
      "testing-5.0.0Beta4",
      "",
      "",
      ""
    ]
  }
}
