{
  "nightly": {
    "commit_message": "Modified: meta.json",
    "commit_sha": "e5850132eb5aa98fa1f74785331655ee21f46c61",
    "description": "Every commit to develop",
    "hide": false,
    "last_updated": "2026-07-09T10:24:06.000Z",
    "last_updated_url": "https://github.com/hotio/sabnzbd/actions/runs/29011478741",
    "tags": [
      "",
      "nightly",
      "nightly-e585013",
      "nightly-0bcb28d5763327489502afdf608d416baed24a21",
      "",
      "",
      ""
    ]
  },
  "release": {
    "commit_message": "Modified: packages.txt",
    "commit_sha": "87cf11e3a66915f67f40d8808a80017823bb519b",
    "description": "Releases",
    "hide": false,
    "last_updated": "2026-07-08T23:05:37.000Z",
    "last_updated_url": "https://github.com/hotio/sabnzbd/actions/runs/28981862234",
    "tags": [
      "latest",
      "release",
      "release-87cf11e",
      "release-5.0.4",
      "release-v5",
      "release-v5.0",
      "release-v5.0.4"
    ]
  },
  "testing": {
    "commit_message": "Modified: meta.json",
    "commit_sha": "cf0a578ef88972156a7992220e742ce8df13ec9f",
    "description": "Pre-releases",
    "hide": false,
    "last_updated": "2026-07-08T21:06:05.000Z",
    "last_updated_url": "https://github.com/hotio/sabnzbd/actions/runs/28975719325",
    "tags": [
      "",
      "testing",
      "testing-cf0a578",
      "testing-5.1.0Beta2",
      "",
      "",
      ""
    ]
  }
}
