{
  "nightly": {
    "commit_message": "Version update: 594e303265481899d9c6db46d654fef582d9f214 => 69208db69920af5180fd5e24c1496d77e8ed3b93",
    "commit_sha": "b270055d5776bed74fac32491113bf94a8710498",
    "description": "Every commit to develop",
    "hide": false,
    "last_updated": "2026-03-13T10:42:41.000Z",
    "last_updated_url": "https://github.com/hotio/sabnzbd/actions/runs/23047219088",
    "tags": [
      "",
      "nightly",
      "nightly-b270055",
      "nightly-69208db69920af5180fd5e24c1496d77e8ed3b93",
      "",
      "",
      ""
    ]
  },
  "release": {
    "commit_message": "Upstream update: alpinevpn-e5bbee4 => alpinevpn-9abb66b",
    "commit_sha": "48d37cb3372619463a25e66c0e4e9e4195bca12c",
    "description": "Releases",
    "hide": false,
    "last_updated": "2026-02-23T03:44:18.000Z",
    "last_updated_url": "https://github.com/hotio/sabnzbd/actions/runs/22292136862",
    "tags": [
      "latest",
      "release",
      "release-48d37cb",
      "release-4.5.5",
      "release-v4",
      "release-v4.5",
      "release-v4.5.5"
    ]
  },
  "testing": {
    "commit_message": "Version update: 5.0.0Beta1 => 5.0.0Beta2",
    "commit_sha": "ed3f736adb5c08b6b0fc986b06d466d3d4d41601",
    "description": "Pre-releases",
    "hide": false,
    "last_updated": "2026-02-27T14:27:09.000Z",
    "last_updated_url": "https://github.com/hotio/sabnzbd/actions/runs/22490144729",
    "tags": [
      "",
      "testing",
      "testing-ed3f736",
      "testing-5.0.0Beta2",
      "",
      "",
      ""
    ]
  }
}
