{
  "nightly": {
    "commit_message": "Modified: meta.json",
    "commit_sha": "1c8faf4b62dcc735e964d095f38ffe36fdf183be",
    "description": "Every commit to develop",
    "hide": false,
    "last_updated": "2026-06-08T22:25:39.000Z",
    "last_updated_url": "https://github.com/hotio/sabnzbd/actions/runs/27170914858",
    "tags": [
      "",
      "nightly",
      "nightly-1c8faf4",
      "nightly-740eb442a8ab62081674b9b617bd1c5a630d4b84",
      "",
      "",
      ""
    ]
  },
  "release": {
    "commit_message": "Modified: meta.json",
    "commit_sha": "d9901aa1c30a39f40fe1fd6e520d4d8a5d2c2577",
    "description": "Releases",
    "hide": false,
    "last_updated": "2026-05-23T13:34:17.000Z",
    "last_updated_url": "https://github.com/hotio/sabnzbd/actions/runs/26334082571",
    "tags": [
      "latest",
      "release",
      "release-d9901aa",
      "release-5.0.3",
      "release-v5",
      "release-v5.0",
      "release-v5.0.3"
    ]
  },
  "testing": {
    "commit_message": "Modified: meta.json",
    "commit_sha": "65daef7db77a32e4201c0a892315d23aae1b6951",
    "description": "Pre-releases",
    "hide": false,
    "last_updated": "2026-06-07T12:20:06.000Z",
    "last_updated_url": "https://github.com/hotio/sabnzbd/actions/runs/27092387403",
    "tags": [
      "",
      "testing",
      "testing-65daef7",
      "testing-5.0.4RC1",
      "",
      "",
      ""
    ]
  }
}
