{
  "nightly": {
    "commit_message": "Upstream update: alpinevpn-7ce2a5c => alpinevpn-24b1ed4",
    "commit_sha": "959a7ad3070934882d6938a7e4868f85c96ff7c4",
    "description": "Every commit to develop",
    "hide": false,
    "last_updated": "2026-01-28T05:23:37.000Z",
    "last_updated_url": "https://github.com/hotio/seerr/actions/runs/21426214362",
    "tags": [
      "",
      "nightly",
      "nightly-959a7ad",
      "nightly-5bd31040c06e555e3a7c93c3af526dd70699974f",
      "",
      "",
      ""
    ]
  },
  "release": {
    "commit_message": "Upstream update: alpinevpn-46fe99f => alpinevpn-7ce2a5c",
    "commit_sha": "05ef9c399b294d342f9dcd11cfb516430cb59d80",
    "description": "Releases",
    "hide": false,
    "last_updated": "2026-01-26T10:20:56.000Z",
    "last_updated_url": "https://github.com/hotio/seerr/actions/runs/21354181861",
    "tags": [
      "latest",
      "release",
      "release-05ef9c3",
      "release-2.7.3",
      "release-v2",
      "release-v2.7",
      "release-v2.7.3"
    ]
  }
}
