{
  "nightly": {
    "commit_message": "Version update: 0.24.3.65534+337fe1c7 => 0.24.3.65534+92b49b7a",
    "commit_sha": "a0f90751685e729f98b4d9d57dd812c8e304362f",
    "description": "Canary releases",
    "last_updated": "2026-01-22T19:55:35.000Z",
    "last_updated_url": "https://github.com/hotio/slskd/actions/runs/21262851779",
    "tags": [
      "",
      "nightly",
      "nightly-a0f9075",
      "nightly-0.24.3.65534-92b49b7a",
      "",
      "",
      ""
    ]
  },
  "release": {
    "commit_message": "Upstream update: alpinevpn-5648cae => alpinevpn-3f254df",
    "commit_sha": "3c224791eec3e4c78e11d0169ee6030e27f89b75",
    "description": "Releases",
    "hide": false,
    "last_updated": "2026-01-22T11:29:47.000Z",
    "last_updated_url": "https://github.com/hotio/slskd/actions/runs/21246776140",
    "tags": [
      "latest",
      "release",
      "release-3c22479",
      "release-0.24.3",
      "release-v0",
      "release-v0.24",
      "release-v0.24.3"
    ]
  }
}
