{
  "nightly": {
    "commit_message": "",
    "commit_sha": "e33fd034b6b9f90b051b7e237fc9e6404b583f95",
    "description": "Canary releases",
    "last_updated": "2026-05-15T00:04:02.000Z",
    "last_updated_url": "https://github.com/hotio/slskd/actions/runs/25916045195",
    "tags": [
      "",
      "nightly",
      "nightly-e33fd03",
      "nightly-0.25.1.65534-9bb82212",
      "",
      "",
      ""
    ]
  },
  "release": {
    "commit_message": "Upstream or Packages File update",
    "commit_sha": "1150bd87b87ebfa354af2a6bb07d3703efe1d502",
    "description": "Releases",
    "hide": false,
    "last_updated": "2026-05-12T05:18:58.000Z",
    "last_updated_url": "https://github.com/hotio/slskd/actions/runs/25715029971",
    "tags": [
      "latest",
      "release",
      "release-1150bd8",
      "release-0.25.1",
      "release-v0",
      "release-v0.25",
      "release-v0.25.1"
    ]
  }
}
