{
  "nightly": {
    "commit_message": "Upstream update: alpinevpn-5648cae => alpinevpn-3f254df",
    "commit_sha": "73e11d7b7cc768305f80d2c0a5d8ef576e928fea",
    "description": "Canary releases",
    "last_updated": "2026-01-22T11:29:46.000Z",
    "last_updated_url": "https://github.com/hotio/slskd/actions/runs/21246775549",
    "tags": [
      "",
      "nightly",
      "nightly-73e11d7",
      "nightly-0.24.3.65534-337fe1c7",
      "",
      "",
      ""
    ]
  },
  "release": {
    "commit_message": "add validated file in app image",
    "commit_sha": "ff81da0f5d1f30373baa29f19a698a788512fa1a",
    "description": "Releases",
    "hide": false,
    "last_updated": "2026-01-22T11:22:45.000Z",
    "last_updated_url": "https://github.com/hotio/slskd/actions/runs/21246581127",
    "tags": [
      "latest",
      "release",
      "release-ff81da0",
      "release-0.24.3",
      "release-v0",
      "release-v0.24",
      "release-v0.24.3"
    ]
  }
}
