{
  "nightly": {
    "commit_message": "Upstream update: alpinevpn-5b650ae => alpinevpn-b4dc175",
    "commit_sha": "135e2acb4be817c829da0c3d4730d8464dd08ea2",
    "description": "develop/v4-nightly",
    "hide": false,
    "last_updated": "2026-01-11T12:29:23.000Z",
    "last_updated_url": "https://github.com/hotio/sonarr/actions/runs/20895147248",
    "latest": false,
    "tags": [
      "nightly",
      "nightly-4.0.16.2946",
      "nightly-135e2ac",
      "",
      "",
      ""
    ]
  },
  "release": {
    "commit_message": "Upstream update: alpinevpn-0904450 => alpinevpn-5b650ae",
    "commit_sha": "2a8851725bb8f0152cc4f12065d89bf43d1b1ad8",
    "description": "main/v4-stable",
    "hide": false,
    "last_updated": "2026-01-11T08:20:03.000Z",
    "last_updated_url": "https://github.com/hotio/sonarr/actions/runs/20892090921",
    "latest": true,
    "tags": [
      "release",
      "release-4.0.16.2944",
      "release-2a88517",
      "",
      "",
      ""
    ]
  }
}
