{
  "release": {
    "commit_message": "Upstream update: alpinevpn-e7368e6 => alpinevpn-156b37c",
    "commit_sha": "19eeda005c3df043ea76a8eed061f0dd9cf4b4fd",
    "description": "Releases",
    "hide": false,
    "last_updated": "2026-01-16T08:34:11.000Z",
    "last_updated_url": "https://github.com/hotio/tautulli/actions/runs/21060555716",
    "tags": [
      "latest",
      "release",
      "release-19eeda0",
      "release-2.16.0",
      "release-v2",
      "release-v2.16",
      "release-v2.16.0"
    ]
  },
  "testing": {
    "commit_message": "Upstream update: alpinevpn-e7368e6 => alpinevpn-156b37c",
    "commit_sha": "013ad025a0d5f28f6814e0ac34b63b95ecb847b5",
    "description": "Pre-releases",
    "hide": false,
    "last_updated": "2026-01-16T08:34:11.000Z",
    "last_updated_url": "https://github.com/hotio/tautulli/actions/runs/21060555892",
    "tags": [
      "",
      "testing",
      "testing-013ad02",
      "testing-2.16.0",
      "testing-v2",
      "testing-v2.16",
      "testing-v2.16.0"
    ]
  }
}
