{
  "nightly": {
    "commit_message": "Upstream update: null => alpinevpn-30708ff",
    "commit_sha": "a228ca9b882aacd9a6074da40c13ff5e3ff24211",
    "description": "Every commit to master",
    "hide": false,
    "last_updated": "2026-01-09T05:41:17.000Z",
    "last_updated_url": "https://github.com/hotio/unpackerr/actions/runs/20842482034",
    "latest": false,
    "tags": [
      "nightly",
      "nightly-1b830500d18707e639f56d6d0d17cf059f74feca",
      "nightly-a228ca9",
      "",
      "",
      ""
    ]
  },
  "release": {
    "commit_message": "Upstream update: null => alpinevpn-30708ff",
    "commit_sha": "48a8ad9f4e633cddcd722d71d36cf56d7e4efc80",
    "description": "Releases",
    "hide": false,
    "last_updated": "2026-01-09T05:41:18.000Z",
    "last_updated_url": "https://github.com/hotio/unpackerr/actions/runs/20842482201",
    "latest": true,
    "tags": [
      "release",
      "release-0.14.5",
      "release-48a8ad9",
      "release-v0",
      "release-v0.14",
      "release-v0.14.5"
    ]
  },
  "testing": {
    "commit_message": "Upstream image update",
    "commit_sha": "50751cba68c2ed578b3b71b001e52acab425616d",
    "description": "Pre-releases",
    "hide": false,
    "last_updated": "2026-01-07T03:58:06.000Z",
    "last_updated_url": "https://github.com/hotio/unpackerr/actions/runs/20770111050",
    "latest": false,
    "tags": [
      "testing",
      "testing-0.14.5",
      "testing-50751cb",
      "testing-v0",
      "testing-v0.14",
      "testing-v0.14.5"
    ]
  }
}
