{
  "v2": {
    "commit_message": "Upstream update: alpinevpn-2c8fbe3 => alpinevpn-6f109b5",
    "commit_sha": "ff2ab7361e0eebb02eafd05f04f9390cb7d6825a",
    "description": "v2",
    "last_updated": "2026-01-22T06:03:45.000Z",
    "last_updated_url": "https://github.com/hotio/whisparr/actions/runs/21237961294",
    "tags": [
      "latest",
      "v2",
      "v2-ff2ab73",
      "v2-2.0.0.2151",
      "",
      "",
      ""
    ]
  },
  "v3": {
    "commit_message": "Upstream update: alpinevpn-2c8fbe3 => alpinevpn-6f109b5",
    "commit_sha": "0c621e0337d0dc99f8a299fed326922541cac521",
    "description": "eros",
    "hide": false,
    "last_updated": "2026-01-22T06:03:48.000Z",
    "last_updated_url": "https://github.com/hotio/whisparr/actions/runs/21237962210",
    "tags": [
      "",
      "v3",
      "v3-0c621e0",
      "v3-3.2.1-release.65",
      "v3-v3",
      "v3-v3.2",
      "v3-v3.2.1"
    ]
  },
  "v3-develop": {
    "commit_message": "Upstream update: alpinevpn-2c8fbe3 => alpinevpn-6f109b5",
    "commit_sha": "dc9ea45cd1218c05fe7881f80f5206d75e83554d",
    "description": "eros-develop",
    "last_updated": "2026-01-22T06:03:46.000Z",
    "last_updated_url": "https://github.com/hotio/whisparr/actions/runs/21237961557",
    "tags": [
      "",
      "v3-develop",
      "v3-develop-dc9ea45",
      "v3-develop-3.2.1-develop.74",
      "v3-develop-v3",
      "v3-develop-v3.2",
      "v3-develop-v3.2.1"
    ]
  }
}
