{
  "nightly": {
    "commit_message": "Upstream update: alpinevpn-b4dc175 => alpinevpn-9c717da",
    "commit_sha": "83008ba282b6d1e5dfcc25e98993a5fba93e3119",
    "description": "nightly",
    "hide": false,
    "last_updated": "2026-01-11T16:18:01.000Z",
    "last_updated_url": "https://github.com/hotio/whisparr/actions/runs/20898169752",
    "latest": true,
    "tags": [
      "nightly",
      "nightly-2.0.0.2081",
      "nightly-83008ba",
      "",
      "",
      ""
    ]
  },
  "v3": {
    "commit_message": "Version update: 3.1.0.2093 => 3.1.0.2100",
    "commit_sha": "4bdee1049d4f293d24b7f6000eb0f1138c9c50f3",
    "description": "eros",
    "hide": false,
    "last_updated": "2026-01-12T02:29:59.000Z",
    "last_updated_url": "https://github.com/hotio/whisparr/actions/runs/20906270059",
    "latest": false,
    "tags": [
      "v3",
      "v3-3.1.0.2100",
      "v3-4bdee10",
      "",
      "",
      ""
    ]
  }
}
